{"metadata":{},"options":{"assumptions":{},"compact":false,"sourceMaps":true,"ast":true,"babelrc":false,"configFile":false,"parserOpts":{"sourceType":"module","sourceFileName":"C:\\Users\\snntv\\OneDrive\\Documents\\AI Agent\\projects\\Meteor\\BlueSky\\imports\\ui\\AdminPanel.jsx","plugins":["*","flow","jsx","asyncGenerators","bigInt","classPrivateMethods","classPrivateProperties","classProperties","doExpressions","dynamicImport","exportDefaultFrom","exportExtensions","exportNamespaceFrom","functionBind","functionSent","importMeta","nullishCoalescingOperator","numericSeparator","objectRestSpread","optionalCatchBinding","optionalChaining",["pipelineOperator",{"proposal":"minimal"}],"throwExpressions","topLevelAwait","classProperties","classPrivateProperties","jsx","nullishCoalescingOperator","nullishCoalescingOperator","optionalChaining","optionalChaining","optionalCatchBinding","optionalCatchBinding","classProperties","classPrivateProperties","classPrivateMethods","classProperties","classPrivateProperties","asyncGenerators","asyncGenerators","objectRestSpread","objectRestSpread","logicalAssignment"],"allowImportExportEverywhere":true,"allowReturnOutsideFunction":true,"allowUndeclaredExports":true,"strictMode":false},"caller":{"name":"meteor","arch":"web.browser.legacy"},"sourceFileName":"imports/ui/AdminPanel.jsx","filename":"C:\\Users\\snntv\\OneDrive\\Documents\\AI Agent\\projects\\Meteor\\BlueSky\\imports\\ui\\AdminPanel.jsx","inputSourceMap":{"version":3,"names":["React","useState","AdminPanel","_s","users","setUsers","newUsername","setNewUsername","newPassword","setNewPassword","deleteUsername","setDeleteUsername","handleAddUser","e","preventDefault","trim","alert","newUser","id","Date","now","username","role","handleDeleteUser","find","user","filter","target","value","length","map","textAlign","fontStyle","color","_c","$RefreshReg$"],"sources":["imports/ui/AdminPanel.jsx"],"sourcesContent":["import React, { useState } from 'react';\r\n\r\nexport const AdminPanel = () => {\r\n  const [users, setUsers] = useState([]);\r\n  const [newUsername, setNewUsername] = useState('');\r\n  const [newPassword, setNewPassword] = useState('');\r\n  const [deleteUsername, setDeleteUsername] = useState('');\r\n\r\n  const handleAddUser = (e) => {\r\n    e.preventDefault();\r\n    if (newUsername.trim() === '') {\r\n      alert('Please enter a username.');\r\n      return;\r\n    }\r\n    const newUser = {\r\n      id: Date.now(), // simple unique id\r\n      username: newUsername,\r\n      role: 'User',\r\n    };\r\n    setUsers([...users, newUser]);\r\n    setNewUsername('');\r\n    setNewPassword('');\r\n  };\r\n\r\n  const handleDeleteUser = (e) => {\r\n    e.preventDefault();\r\n    if (deleteUsername.trim() === '') {\r\n      alert('Please enter a username to delete.');\r\n      return;\r\n    }\r\n    if (!users.find(user => user.username === deleteUsername)) {\r\n      alert('User not found.');\r\n      return;\r\n    }\r\n    setUsers(users.filter(user => user.username !== deleteUsername));\r\n    setDeleteUsername('');\r\n  };\r\n\r\n  return (\r\n    <div className=\"admin-panel\">\r\n      <div className=\"admin-header\">\r\n        <h1>Welcome to the Admin Panel</h1>\r\n        <p className=\"admin-user-role\">User as Admin</p>\r\n      </div>\r\n      <div className=\"admin-content\">\r\n        <div className=\"admin-section\">\r\n          <form className=\"admin-form horizontal-form\" onSubmit={handleAddUser}>\r\n            <div className=\"form-group\">\r\n              <label htmlFor=\"username\">User Name</label>\r\n              <input \r\n                type=\"text\" \r\n                id=\"username\" \r\n                name=\"username\" \r\n                placeholder=\"Enter new user's name\" \r\n                value={newUsername}\r\n                onChange={(e) => setNewUsername(e.target.value)}\r\n              />\r\n            </div>\r\n            <div className=\"form-group\">\r\n              <label htmlFor=\"password\">Password</label>\r\n              <input \r\n                type=\"password\" \r\n                id=\"password\" \r\n                name=\"password\" \r\n                placeholder=\"Enter password\" \r\n                value={newPassword}\r\n                onChange={(e) => setNewPassword(e.target.value)}\r\n              />\r\n            </div>\r\n            <button type=\"submit\" className=\"admin-button\">Add User</button>\r\n          </form>\r\n        </div>\r\n\r\n        <div className=\"admin-section\">\r\n          <form className=\"admin-form horizontal-form\" onSubmit={handleDeleteUser}>\r\n            <div className=\"form-group\">\r\n              <label htmlFor=\"delete-username\">User Name</label>\r\n              <input \r\n                type=\"text\" \r\n                id=\"delete-username\" \r\n                name=\"delete-username\" \r\n                placeholder=\"Enter user's name to delete\" \r\n                value={deleteUsername}\r\n                onChange={(e) => setDeleteUsername(e.target.value)}\r\n              />\r\n            </div>\r\n            <button type=\"submit\" className=\"admin-button danger\">Delete User</button>\r\n          </form>\r\n        </div>\r\n\r\n        <div className=\"admin-section\">\r\n          <h2>User List</h2>\r\n          <table className=\"users-table\">\r\n            <thead>\r\n              <tr>\r\n                <th>User Name</th>\r\n                <th>Role</th>\r\n              </tr>\r\n            </thead>\r\n            <tbody>\r\n              {users.length > 0 ? (\r\n                users.map(user => (\r\n                  <tr key={user.id}>\r\n                    <td>{user.username}</td>\r\n                    <td>{user.role}</td>\r\n                  </tr>\r\n                ))\r\n              ) : (\r\n                <tr>\r\n                  <td colSpan=\"2\" style={{ textAlign: 'center', fontStyle: 'italic', color: 'rgba(255, 255, 255, 0.5)' }}>No users found.</td>\r\n                </tr>\r\n              )}\r\n            </tbody>\r\n          </table>\r\n        </div>\r\n      </div>\r\n    </div>\r\n  );\r\n};\r\n"],"mappings":";;AAAA,OAAOA,KAAK,IAAIC,QAAQ,QAAQ,OAAO;AAEvC,OAAO,MAAMC,UAAU,GAAGA,CAAA,KAAM;EAAAC,EAAA;EAC9B,MAAM,CAACC,KAAK,EAAEC,QAAQ,CAAC,GAAGJ,QAAQ,CAAC,EAAE,CAAC;EACtC,MAAM,CAACK,WAAW,EAAEC,cAAc,CAAC,GAAGN,QAAQ,CAAC,EAAE,CAAC;EAClD,MAAM,CAACO,WAAW,EAAEC,cAAc,CAAC,GAAGR,QAAQ,CAAC,EAAE,CAAC;EAClD,MAAM,CAACS,cAAc,EAAEC,iBAAiB,CAAC,GAAGV,QAAQ,CAAC,EAAE,CAAC;EAExD,MAAMW,aAAa,GAAIC,CAAC,IAAK;IAC3BA,CAAC,CAACC,cAAc,CAAC,CAAC;IAClB,IAAIR,WAAW,CAACS,IAAI,CAAC,CAAC,KAAK,EAAE,EAAE;MAC7BC,KAAK,CAAC,0BAA0B,CAAC;MACjC;IACF;IACA,MAAMC,OAAO,GAAG;MACdC,EAAE,EAAEC,IAAI,CAACC,GAAG,CAAC,CAAC;MAAE;MAChBC,QAAQ,EAAEf,WAAW;MACrBgB,IAAI,EAAE;IACR,CAAC;IACDjB,QAAQ,CAAC,CAAC,GAAGD,KAAK,EAAEa,OAAO,CAAC,CAAC;IAC7BV,cAAc,CAAC,EAAE,CAAC;IAClBE,cAAc,CAAC,EAAE,CAAC;EACpB,CAAC;EAED,MAAMc,gBAAgB,GAAIV,CAAC,IAAK;IAC9BA,CAAC,CAACC,cAAc,CAAC,CAAC;IAClB,IAAIJ,cAAc,CAACK,IAAI,CAAC,CAAC,KAAK,EAAE,EAAE;MAChCC,KAAK,CAAC,oCAAoC,CAAC;MAC3C;IACF;IACA,IAAI,CAACZ,KAAK,CAACoB,IAAI,CAACC,IAAI,IAAIA,IAAI,CAACJ,QAAQ,KAAKX,cAAc,CAAC,EAAE;MACzDM,KAAK,CAAC,iBAAiB,CAAC;MACxB;IACF;IACAX,QAAQ,CAACD,KAAK,CAACsB,MAAM,CAACD,IAAI,IAAIA,IAAI,CAACJ,QAAQ,KAAKX,cAAc,CAAC,CAAC;IAChEC,iBAAiB,CAAC,EAAE,CAAC;EACvB,CAAC;EAED,OACE,CAAC,GAAG,CAAC,SAAS,CAAC,aAAa,CAAC;AACjC,MAAM,CAAC,GAAG,CAAC,SAAS,CAAC,cAAc,CAAC;AACpC,QAAQ,CAAC,EAAE,CAAC,0BAA0B,EAAE,EAAE,CAAC;AAC3C,QAAQ,CAAC,CAAC,CAAC,SAAS,CAAC,iBAAiB,CAAC,aAAa,EAAE,CAAC,CAAC;AACxD,MAAM,EAAE,GAAG,CAAC;AACZ,MAAM,CAAC,GAAG,CAAC,SAAS,CAAC,eAAe,CAAC;AACrC,QAAQ,CAAC,GAAG,CAAC,SAAS,CAAC,eAAe,CAAC;AACvC,UAAU,CAAC,IAAI,CAAC,SAAS,CAAC,4BAA4B,CAAC,QAAQ,CAAC,CAACC,aAAa,CAAC,CAAC;AAChF,YAAY,CAAC,GAAG,CAAC,SAAS,CAAC,YAAY,CAAC;AACxC,cAAc,CAAC,KAAK,CAAC,OAAO,CAAC,UAAU,CAAC,SAAS,EAAE,KAAK,CAAC;AACzD,cAAc,CAAC,KAAK,CACJ,IAAI,CAAC,MAAM,CACX,EAAE,CAAC,UAAU,CACb,IAAI,CAAC,UAAU,CACf,WAAW,CAAC,uBAAuB,CACnC,KAAK,CAAC,CAACN,WAAW,CAAC,CACnB,QAAQ,CAAC,CAAEO,CAAC,IAAKN,cAAc,CAACM,CAAC,CAACc,MAAM,CAACC,KAAK,CAAC,CAAC,GAChD;AAChB,YAAY,EAAE,GAAG,CAAC;AAClB,YAAY,CAAC,GAAG,CAAC,SAAS,CAAC,YAAY,CAAC;AACxC,cAAc,CAAC,KAAK,CAAC,OAAO,CAAC,UAAU,CAAC,QAAQ,EAAE,KAAK,CAAC;AACxD,cAAc,CAAC,KAAK,CACJ,IAAI,CAAC,UAAU,CACf,EAAE,CAAC,UAAU,CACb,IAAI,CAAC,UAAU,CACf,WAAW,CAAC,gBAAgB,CAC5B,KAAK,CAAC,CAACpB,WAAW,CAAC,CACnB,QAAQ,CAAC,CAAEK,CAAC,IAAKJ,cAAc,CAACI,CAAC,CAACc,MAAM,CAACC,KAAK,CAAC,CAAC,GAChD;AAChB,YAAY,EAAE,GAAG,CAAC;AAClB,YAAY,CAAC,MAAM,CAAC,IAAI,CAAC,QAAQ,CAAC,SAAS,CAAC,cAAc,CAAC,QAAQ,EAAE,MAAM,CAAC;AAC5E,UAAU,EAAE,IAAI,CAAC;AACjB,QAAQ,EAAE,GAAG,CAAC;AACd;AACA,QAAQ,CAAC,GAAG,CAAC,SAAS,CAAC,eAAe,CAAC;AACvC,UAAU,CAAC,IAAI,CAAC,SAAS,CAAC,4BAA4B,CAAC,QAAQ,CAAC,CAACL,gBAAgB,CAAC,CAAC;AACnF,YAAY,CAAC,GAAG,CAAC,SAAS,CAAC,YAAY,CAAC;AACxC,cAAc,CAAC,KAAK,CAAC,OAAO,CAAC,iBAAiB,CAAC,SAAS,EAAE,KAAK,CAAC;AAChE,cAAc,CAAC,KAAK,CACJ,IAAI,CAAC,MAAM,CACX,EAAE,CAAC,iBAAiB,CACpB,IAAI,CAAC,iBAAiB,CACtB,WAAW,CAAC,6BAA6B,CACzC,KAAK,CAAC,CAACb,cAAc,CAAC,CACtB,QAAQ,CAAC,CAAEG,CAAC,IAAKF,iBAAiB,CAACE,CAAC,CAACc,MAAM,CAACC,KAAK,CAAC,CAAC,GACnD;AAChB,YAAY,EAAE,GAAG,CAAC;AAClB,YAAY,CAAC,MAAM,CAAC,IAAI,CAAC,QAAQ,CAAC,SAAS,CAAC,qBAAqB,CAAC,WAAW,EAAE,MAAM,CAAC;AACtF,UAAU,EAAE,IAAI,CAAC;AACjB,QAAQ,EAAE,GAAG,CAAC;AACd;AACA,QAAQ,CAAC,GAAG,CAAC,SAAS,CAAC,eAAe,CAAC;AACvC,UAAU,CAAC,EAAE,CAAC,SAAS,EAAE,EAAE,CAAC;AAC5B,UAAU,CAAC,KAAK,CAAC,SAAS,CAAC,aAAa,CAAC;AACzC,YAAY,CAAC,KAAK,CAAC;AACnB,cAAc,CAAC,EAAE,CAAC;AAClB,gBAAgB,CAAC,EAAE,CAAC,SAAS,EAAE,EAAE,CAAC;AAClC,gBAAgB,CAAC,EAAE,CAAC,IAAI,EAAE,EAAE,CAAC;AAC7B,cAAc,EAAE,EAAE,CAAC;AACnB,YAAY,EAAE,KAAK,CAAC;AACpB,YAAY,CAAC,KAAK,CAAC;AACnB,cAAc,CAACxB,KAAK,CAACyB,MAAM,GAAG,CAAC,GACfzB,KAAK,CAAC0B,GAAG,CAACL,IAAI,IACZ,CAAC,EAAE,CAAC,GAAG,CAAC,CAACA,IAAI,CAACP,EAAE,CAAC,CAAC;AACpC,oBAAoB,CAAC,EAAE,CAAC,CAACO,IAAI,CAACJ,QAAQ,CAAC,EAAE,EAAE,CAAC;AAC5C,oBAAoB,CAAC,EAAE,CAAC,CAACI,IAAI,CAACH,IAAI,CAAC,EAAE,EAAE,CAAC;AACxC,kBAAkB,EAAE,EAAE,CACL,CAAC,GAEF,CAAC,EAAE,CAAC;AACpB,kBAAkB,CAAC,EAAE,CAAC,OAAO,CAAC,GAAG,CAAC,KAAK,CAAC,CAAC;gBAAES,SAAS,EAAE,QAAQ;gBAAEC,SAAS,EAAE,QAAQ;gBAAEC,KAAK,EAAE;cAA2B,CAAC,CAAC,CAAC,eAAe,EAAE,EAAE,CAAC;AAC9I,gBAAgB,EAAE,EAAE,CACL,CAAC;AAChB,YAAY,EAAE,KAAK,CAAC;AACpB,UAAU,EAAE,KAAK,CAAC;AAClB,QAAQ,EAAE,GAAG,CAAC;AACd,MAAM,EAAE,GAAG,CAAC;AACZ,IAAI,EAAE,GAAG,CAAC;AAEV,CAAC;AAAC9B,EAAA,CApHWD,UAAU;AAAAgC,EAAA,GAAVhC,UAAU;AAAA,IAAAgC,EAAA;AAAAC,YAAA,CAAAD,EAAA","ignoreList":[]},"targets":{},"cloneInputAst":true,"browserslistConfigFile":false,"passPerPreset":false,"envName":"development","cwd":"C:\\Users\\snntv\\OneDrive\\Documents\\AI Agent\\projects\\Meteor\\BlueSky","root":"C:\\Users\\snntv\\OneDrive\\Documents\\AI Agent\\projects\\Meteor\\BlueSky","rootMode":"root","plugins":[{"key":"base$0","visitor":{"_exploded":true,"_verified":true},"options":{},"externalDependencies":[]},{"key":"base$0$0","visitor":{"Program":{"enter":[null],"exit":[null]},"_exploded":true,"_verified":true},"options":{"avoidModernSyntax":true,"enforceStrictMode":false,"dynamicImport":true},"externalDependencies":[]},{"key":"transform-runtime","visitor":{"ObjectPattern":{"enter":[null]},"BinaryExpression":{"enter":[null]},"MemberExpression":{"enter":[null]},"OptionalMemberExpression":{"enter":[null]},"Identifier":{"enter":[null]},"JSXIdentifier":{"enter":[null]}},"options":{"version":"7.17.2","helpers":true,"useESModules":false,"corejs":false},"externalDependencies":[]},{"key":"proposal-class-properties","visitor":{"ExportDefaultDeclaration":{"enter":[null]},"_exploded":true,"_verified":true,"ClassExpression":{"enter":[null]},"ClassDeclaration":{"enter":[null]}},"options":{"loose":true},"externalDependencies":[]},{"key":"base$0$3","visitor":{"FunctionExpression":{"exit":[null]},"_exploded":true,"_verified":true},"options":{},"externalDependencies":[]},{"key":"base$0$4","visitor":{"ForInStatement":{"enter":[null]},"_exploded":true,"_verified":true},"options":{},"externalDependencies":[]},{"key":"transform-react-jsx","visitor":{"JSXNamespacedName":{"enter":[null]},"JSXSpreadChild":{"enter":[null]},"Program":{"enter":[null]},"JSXFragment":{"exit":[null]},"JSXElement":{"exit":[null]},"JSXAttribute":{"enter":[null]}},"options":{"pragma":"React.createElement","pragmaFrag":"React.Fragment","runtime":"classic","throwIfNamespace":true,"useBuiltIns":false},"externalDependencies":[]},{"key":"transform-react-display-name","visitor":{"ExportDefaultDeclaration":{"enter":[null]},"CallExpression":{"enter":[null]},"_exploded":true,"_verified":true},"options":{},"externalDependencies":[]},{"key":"transform-react-pure-annotations","visitor":{"CallExpression":{"enter":[null]},"_exploded":true,"_verified":true},"options":{},"externalDependencies":[]},{"key":"syntax-nullish-coalescing-operator","visitor":{"_exploded":true,"_verified":true},"options":{},"externalDependencies":[]},{"key":"proposal-nullish-coalescing-operator","visitor":{"LogicalExpression":{"enter":[null]}},"options":{},"externalDependencies":[]},{"key":"syntax-optional-chaining","visitor":{"_exploded":true,"_verified":true},"options":{},"externalDependencies":[]},{"key":"proposal-optional-chaining","visitor":{"OptionalCallExpression":{"enter":[null]},"OptionalMemberExpression":{"enter":[null]}},"options":{},"externalDependencies":[]},{"key":"syntax-optional-catch-binding","visitor":{"_exploded":true,"_verified":true},"options":{},"externalDependencies":[]},{"key":"proposal-optional-catch-binding","visitor":{"CatchClause":{"enter":[null]}},"options":{},"externalDependencies":[]},{"key":"syntax-class-properties","visitor":{"_exploded":true,"_verified":true},"options":{},"externalDependencies":[]},{"key":"proposal-class-properties","visitor":{"ExportDefaultDeclaration":{"enter":[null]},"_exploded":true,"_verified":true,"ClassExpression":{"enter":[null]},"ClassDeclaration":{"enter":[null]}},"options":{},"externalDependencies":[]},{"key":"syntax-async-generators","visitor":{"_exploded":true,"_verified":true},"options":{},"externalDependencies":[]},{"key":"proposal-async-generator-functions","visitor":{"Program":{"enter":[null]}},"options":{},"externalDependencies":[]},{"key":"syntax-object-rest-spread","visitor":{"_exploded":true,"_verified":true},"options":{},"externalDependencies":[]},{"key":"proposal-object-rest-spread","visitor":{"VariableDeclarator":{"enter":[null]},"ExportNamedDeclaration":{"enter":[null]},"CatchClause":{"enter":[null]},"AssignmentExpression":{"enter":[null]},"ArrayPattern":{"enter":[null]},"ObjectExpression":{"enter":[null]},"FunctionDeclaration":{"enter":[null]},"FunctionExpression":{"enter":[null]},"ObjectMethod":{"enter":[null]},"ArrowFunctionExpression":{"enter":[null]},"ClassMethod":{"enter":[null]},"ClassPrivateMethod":{"enter":[null]},"ForInStatement":{"enter":[null]},"ForOfStatement":{"enter":[null]}},"options":{},"externalDependencies":[]},{"key":"proposal-logical-assignment-operators","visitor":{"AssignmentExpression":{"enter":[null]}},"options":{},"externalDependencies":[]},{"key":"transform-arrow-functions","visitor":{"ArrowFunctionExpression":{"enter":[null]},"_exploded":true,"_verified":true},"options":{},"externalDependencies":[]},{"key":"transform-block-scoped-functions","visitor":{"BlockStatement":{"enter":[null]},"SwitchCase":{"enter":[null]},"_exploded":true,"_verified":true},"options":{},"externalDependencies":[]},{"key":"transform-block-scoping","visitor":{"VariableDeclaration":{"enter":[null,null]},"BlockStatement":{"enter":[null]},"SwitchCase":{"enter":[null]},"ClassDeclaration":{"enter":[null]},"DoWhileStatement":{"enter":[null]},"ForInStatement":{"enter":[null]},"ForStatement":{"enter":[null]},"WhileStatement":{"enter":[null]},"ForOfStatement":{"enter":[null]},"_exploded":true,"_verified":true},"options":{},"externalDependencies":[]},{"key":"transform-classes","visitor":{"ExportDefaultDeclaration":{"enter":[null]},"ClassDeclaration":{"enter":[null]},"ClassExpression":{"enter":[null]},"_exploded":true,"_verified":true},"options":{"loose":true},"externalDependencies":[]},{"key":"transform-computed-properties","visitor":{"ObjectExpression":{"exit":[null]},"_exploded":true,"_verified":true},"options":{"loose":true},"externalDependencies":[]},{"key":"transform-destructuring","visitor":{"ExportNamedDeclaration":{"enter":[null]},"CatchClause":{"enter":[null]},"AssignmentExpression":{"enter":[null]},"VariableDeclaration":{"enter":[null]},"_exploded":true,"_verified":true,"ForInStatement":{"enter":[null]},"ForOfStatement":{"enter":[null]}},"options":{},"externalDependencies":[]},{"key":"transform-for-of","visitor":{"ForOfStatement":{"enter":[null]},"_exploded":true,"_verified":true},"options":{"loose":true},"externalDependencies":[]},{"key":"transform-literals","visitor":{"NumericLiteral":{"enter":[null]},"StringLiteral":{"enter":[null]},"_exploded":true,"_verified":true},"options":{},"externalDependencies":[]},{"key":"transform-object-super","visitor":{"ObjectExpression":{"enter":[null]},"_exploded":true,"_verified":true,"DoWhileStatement":{"exit":[null]},"ForInStatement":{"exit":[null]},"ForStatement":{"exit":[null]},"WhileStatement":{"exit":[null]},"ForOfStatement":{"exit":[null]}},"options":{},"externalDependencies":[]},{"key":"transform-parameters","visitor":{"_exploded":true,"_verified":true,"FunctionDeclaration":{"enter":[null]},"FunctionExpression":{"enter":[null]},"ObjectMethod":{"enter":[null]},"ArrowFunctionExpression":{"enter":[null]},"ClassMethod":{"enter":[null]},"ClassPrivateMethod":{"enter":[null]}},"options":{},"externalDependencies":[]},{"key":"transform-shorthand-properties","visitor":{"ObjectMethod":{"enter":[null]},"ObjectProperty":{"enter":[null]},"_exploded":true,"_verified":true},"options":{},"externalDependencies":[]},{"key":"transform-spread","visitor":{"ArrayExpression":{"enter":[null]},"CallExpression":{"enter":[null]},"NewExpression":{"enter":[null]},"_exploded":true,"_verified":true},"options":{},"externalDependencies":[]},{"key":"transform-sticky-regex","visitor":{"RegExpLiteral":{"enter":[null]},"_exploded":true,"_verified":true},"options":{},"externalDependencies":[]},{"key":"transform-template-literals","visitor":{"TaggedTemplateExpression":{"enter":[null]},"TemplateLiteral":{"enter":[null]},"_exploded":true,"_verified":true},"options":{"loose":true},"externalDependencies":[]},{"key":"transform-typeof-symbol","visitor":{"UnaryExpression":{"enter":[null]},"_exploded":true,"_verified":true,"BlockStatement":{"enter":[null]},"CatchClause":{"enter":[null]},"DoWhileStatement":{"enter":[null]},"ForInStatement":{"enter":[null]},"ForStatement":{"enter":[null]},"FunctionDeclaration":{"enter":[null]},"FunctionExpression":{"enter":[null]},"Program":{"enter":[null]},"ObjectMethod":{"enter":[null]},"SwitchStatement":{"enter":[null]},"WhileStatement":{"enter":[null]},"ArrowFunctionExpression":{"enter":[null]},"ClassExpression":{"enter":[null]},"ClassDeclaration":{"enter":[null]},"ForOfStatement":{"enter":[null]},"ClassMethod":{"enter":[null]},"ClassPrivateMethod":{"enter":[null]},"StaticBlock":{"enter":[null]},"TSModuleBlock":{"enter":[null]},"AssignmentPattern":{"enter":[null]},"ArrayPattern":{"enter":[null]},"ObjectPattern":{"enter":[null]}},"options":{},"externalDependencies":[]},{"key":"transform-unicode-regex","visitor":{"RegExpLiteral":{"enter":[null]},"_exploded":true,"_verified":true},"options":{},"externalDependencies":[]},{"key":"transform-property-literals","visitor":{"ObjectProperty":{"exit":[null]},"_exploded":true,"_verified":true},"options":{},"externalDependencies":[]},{"key":"transform-exponentiation-operator","visitor":{"AssignmentExpression":{"enter":[null]},"BinaryExpression":{"enter":[null]},"_exploded":true,"_verified":true},"options":{},"externalDependencies":[]},{"key":"transform-regenerator","visitor":{"ObjectMethod":{"enter":[null],"exit":[null]},"ClassMethod":{"enter":[null],"exit":[null]},"ClassPrivateMethod":{"enter":[null],"exit":[null]},"FunctionDeclaration":{"exit":[null]},"FunctionExpression":{"exit":[null]},"ArrowFunctionExpression":{"exit":[null]},"CallExpression":{"enter":[null]},"_exploded":true,"_verified":true},"options":{},"externalDependencies":[]}],"presets":[],"generatorOpts":{"filename":"C:\\Users\\snntv\\OneDrive\\Documents\\AI Agent\\projects\\Meteor\\BlueSky\\imports\\ui\\AdminPanel.jsx","comments":true,"compact":false,"sourceMaps":true,"sourceFileName":"imports/ui/AdminPanel.jsx","inputSourceMap":{"version":3,"names":["React","useState","AdminPanel","_s","users","setUsers","newUsername","setNewUsername","newPassword","setNewPassword","deleteUsername","setDeleteUsername","handleAddUser","e","preventDefault","trim","alert","newUser","id","Date","now","username","role","handleDeleteUser","find","user","filter","target","value","length","map","textAlign","fontStyle","color","_c","$RefreshReg$"],"sources":["imports/ui/AdminPanel.jsx"],"sourcesContent":["import React, { useState } from 'react';\r\n\r\nexport const AdminPanel = () => {\r\n  const [users, setUsers] = useState([]);\r\n  const [newUsername, setNewUsername] = useState('');\r\n  const [newPassword, setNewPassword] = useState('');\r\n  const [deleteUsername, setDeleteUsername] = useState('');\r\n\r\n  const handleAddUser = (e) => {\r\n    e.preventDefault();\r\n    if (newUsername.trim() === '') {\r\n      alert('Please enter a username.');\r\n      return;\r\n    }\r\n    const newUser = {\r\n      id: Date.now(), // simple unique id\r\n      username: newUsername,\r\n      role: 'User',\r\n    };\r\n    setUsers([...users, newUser]);\r\n    setNewUsername('');\r\n    setNewPassword('');\r\n  };\r\n\r\n  const handleDeleteUser = (e) => {\r\n    e.preventDefault();\r\n    if (deleteUsername.trim() === '') {\r\n      alert('Please enter a username to delete.');\r\n      return;\r\n    }\r\n    if (!users.find(user => user.username === deleteUsername)) {\r\n      alert('User not found.');\r\n      return;\r\n    }\r\n    setUsers(users.filter(user => user.username !== deleteUsername));\r\n    setDeleteUsername('');\r\n  };\r\n\r\n  return (\r\n    <div className=\"admin-panel\">\r\n      <div className=\"admin-header\">\r\n        <h1>Welcome to the Admin Panel</h1>\r\n        <p className=\"admin-user-role\">User as Admin</p>\r\n      </div>\r\n      <div className=\"admin-content\">\r\n        <div className=\"admin-section\">\r\n          <form className=\"admin-form horizontal-form\" onSubmit={handleAddUser}>\r\n            <div className=\"form-group\">\r\n              <label htmlFor=\"username\">User Name</label>\r\n              <input \r\n                type=\"text\" \r\n                id=\"username\" \r\n                name=\"username\" \r\n                placeholder=\"Enter new user's name\" \r\n                value={newUsername}\r\n                onChange={(e) => setNewUsername(e.target.value)}\r\n              />\r\n            </div>\r\n            <div className=\"form-group\">\r\n              <label htmlFor=\"password\">Password</label>\r\n              <input \r\n                type=\"password\" \r\n                id=\"password\" \r\n                name=\"password\" \r\n                placeholder=\"Enter password\" \r\n                value={newPassword}\r\n                onChange={(e) => setNewPassword(e.target.value)}\r\n              />\r\n            </div>\r\n            <button type=\"submit\" className=\"admin-button\">Add User</button>\r\n          </form>\r\n        </div>\r\n\r\n        <div className=\"admin-section\">\r\n          <form className=\"admin-form horizontal-form\" onSubmit={handleDeleteUser}>\r\n            <div className=\"form-group\">\r\n              <label htmlFor=\"delete-username\">User Name</label>\r\n              <input \r\n                type=\"text\" \r\n                id=\"delete-username\" \r\n                name=\"delete-username\" \r\n                placeholder=\"Enter user's name to delete\" \r\n                value={deleteUsername}\r\n                onChange={(e) => setDeleteUsername(e.target.value)}\r\n              />\r\n            </div>\r\n            <button type=\"submit\" className=\"admin-button danger\">Delete User</button>\r\n          </form>\r\n        </div>\r\n\r\n        <div className=\"admin-section\">\r\n          <h2>User List</h2>\r\n          <table className=\"users-table\">\r\n            <thead>\r\n              <tr>\r\n                <th>User Name</th>\r\n                <th>Role</th>\r\n              </tr>\r\n            </thead>\r\n            <tbody>\r\n              {users.length > 0 ? (\r\n                users.map(user => (\r\n                  <tr key={user.id}>\r\n                    <td>{user.username}</td>\r\n                    <td>{user.role}</td>\r\n                  </tr>\r\n                ))\r\n              ) : (\r\n                <tr>\r\n                  <td colSpan=\"2\" style={{ textAlign: 'center', fontStyle: 'italic', color: 'rgba(255, 255, 255, 0.5)' }}>No users found.</td>\r\n                </tr>\r\n              )}\r\n            </tbody>\r\n          </table>\r\n        </div>\r\n      </div>\r\n    </div>\r\n  );\r\n};\r\n"],"mappings":";;AAAA,OAAOA,KAAK,IAAIC,QAAQ,QAAQ,OAAO;AAEvC,OAAO,MAAMC,UAAU,GAAGA,CAAA,KAAM;EAAAC,EAAA;EAC9B,MAAM,CAACC,KAAK,EAAEC,QAAQ,CAAC,GAAGJ,QAAQ,CAAC,EAAE,CAAC;EACtC,MAAM,CAACK,WAAW,EAAEC,cAAc,CAAC,GAAGN,QAAQ,CAAC,EAAE,CAAC;EAClD,MAAM,CAACO,WAAW,EAAEC,cAAc,CAAC,GAAGR,QAAQ,CAAC,EAAE,CAAC;EAClD,MAAM,CAACS,cAAc,EAAEC,iBAAiB,CAAC,GAAGV,QAAQ,CAAC,EAAE,CAAC;EAExD,MAAMW,aAAa,GAAIC,CAAC,IAAK;IAC3BA,CAAC,CAACC,cAAc,CAAC,CAAC;IAClB,IAAIR,WAAW,CAACS,IAAI,CAAC,CAAC,KAAK,EAAE,EAAE;MAC7BC,KAAK,CAAC,0BAA0B,CAAC;MACjC;IACF;IACA,MAAMC,OAAO,GAAG;MACdC,EAAE,EAAEC,IAAI,CAACC,GAAG,CAAC,CAAC;MAAE;MAChBC,QAAQ,EAAEf,WAAW;MACrBgB,IAAI,EAAE;IACR,CAAC;IACDjB,QAAQ,CAAC,CAAC,GAAGD,KAAK,EAAEa,OAAO,CAAC,CAAC;IAC7BV,cAAc,CAAC,EAAE,CAAC;IAClBE,cAAc,CAAC,EAAE,CAAC;EACpB,CAAC;EAED,MAAMc,gBAAgB,GAAIV,CAAC,IAAK;IAC9BA,CAAC,CAACC,cAAc,CAAC,CAAC;IAClB,IAAIJ,cAAc,CAACK,IAAI,CAAC,CAAC,KAAK,EAAE,EAAE;MAChCC,KAAK,CAAC,oCAAoC,CAAC;MAC3C;IACF;IACA,IAAI,CAACZ,KAAK,CAACoB,IAAI,CAACC,IAAI,IAAIA,IAAI,CAACJ,QAAQ,KAAKX,cAAc,CAAC,EAAE;MACzDM,KAAK,CAAC,iBAAiB,CAAC;MACxB;IACF;IACAX,QAAQ,CAACD,KAAK,CAACsB,MAAM,CAACD,IAAI,IAAIA,IAAI,CAACJ,QAAQ,KAAKX,cAAc,CAAC,CAAC;IAChEC,iBAAiB,CAAC,EAAE,CAAC;EACvB,CAAC;EAED,OACE,CAAC,GAAG,CAAC,SAAS,CAAC,aAAa,CAAC;AACjC,MAAM,CAAC,GAAG,CAAC,SAAS,CAAC,cAAc,CAAC;AACpC,QAAQ,CAAC,EAAE,CAAC,0BAA0B,EAAE,EAAE,CAAC;AAC3C,QAAQ,CAAC,CAAC,CAAC,SAAS,CAAC,iBAAiB,CAAC,aAAa,EAAE,CAAC,CAAC;AACxD,MAAM,EAAE,GAAG,CAAC;AACZ,MAAM,CAAC,GAAG,CAAC,SAAS,CAAC,eAAe,CAAC;AACrC,QAAQ,CAAC,GAAG,CAAC,SAAS,CAAC,eAAe,CAAC;AACvC,UAAU,CAAC,IAAI,CAAC,SAAS,CAAC,4BAA4B,CAAC,QAAQ,CAAC,CAACC,aAAa,CAAC,CAAC;AAChF,YAAY,CAAC,GAAG,CAAC,SAAS,CAAC,YAAY,CAAC;AACxC,cAAc,CAAC,KAAK,CAAC,OAAO,CAAC,UAAU,CAAC,SAAS,EAAE,KAAK,CAAC;AACzD,cAAc,CAAC,KAAK,CACJ,IAAI,CAAC,MAAM,CACX,EAAE,CAAC,UAAU,CACb,IAAI,CAAC,UAAU,CACf,WAAW,CAAC,uBAAuB,CACnC,KAAK,CAAC,CAACN,WAAW,CAAC,CACnB,QAAQ,CAAC,CAAEO,CAAC,IAAKN,cAAc,CAACM,CAAC,CAACc,MAAM,CAACC,KAAK,CAAC,CAAC,GAChD;AAChB,YAAY,EAAE,GAAG,CAAC;AAClB,YAAY,CAAC,GAAG,CAAC,SAAS,CAAC,YAAY,CAAC;AACxC,cAAc,CAAC,KAAK,CAAC,OAAO,CAAC,UAAU,CAAC,QAAQ,EAAE,KAAK,CAAC;AACxD,cAAc,CAAC,KAAK,CACJ,IAAI,CAAC,UAAU,CACf,EAAE,CAAC,UAAU,CACb,IAAI,CAAC,UAAU,CACf,WAAW,CAAC,gBAAgB,CAC5B,KAAK,CAAC,CAACpB,WAAW,CAAC,CACnB,QAAQ,CAAC,CAAEK,CAAC,IAAKJ,cAAc,CAACI,CAAC,CAACc,MAAM,CAACC,KAAK,CAAC,CAAC,GAChD;AAChB,YAAY,EAAE,GAAG,CAAC;AAClB,YAAY,CAAC,MAAM,CAAC,IAAI,CAAC,QAAQ,CAAC,SAAS,CAAC,cAAc,CAAC,QAAQ,EAAE,MAAM,CAAC;AAC5E,UAAU,EAAE,IAAI,CAAC;AACjB,QAAQ,EAAE,GAAG,CAAC;AACd;AACA,QAAQ,CAAC,GAAG,CAAC,SAAS,CAAC,eAAe,CAAC;AACvC,UAAU,CAAC,IAAI,CAAC,SAAS,CAAC,4BAA4B,CAAC,QAAQ,CAAC,CAACL,gBAAgB,CAAC,CAAC;AACnF,YAAY,CAAC,GAAG,CAAC,SAAS,CAAC,YAAY,CAAC;AACxC,cAAc,CAAC,KAAK,CAAC,OAAO,CAAC,iBAAiB,CAAC,SAAS,EAAE,KAAK,CAAC;AAChE,cAAc,CAAC,KAAK,CACJ,IAAI,CAAC,MAAM,CACX,EAAE,CAAC,iBAAiB,CACpB,IAAI,CAAC,iBAAiB,CACtB,WAAW,CAAC,6BAA6B,CACzC,KAAK,CAAC,CAACb,cAAc,CAAC,CACtB,QAAQ,CAAC,CAAEG,CAAC,IAAKF,iBAAiB,CAACE,CAAC,CAACc,MAAM,CAACC,KAAK,CAAC,CAAC,GACnD;AAChB,YAAY,EAAE,GAAG,CAAC;AAClB,YAAY,CAAC,MAAM,CAAC,IAAI,CAAC,QAAQ,CAAC,SAAS,CAAC,qBAAqB,CAAC,WAAW,EAAE,MAAM,CAAC;AACtF,UAAU,EAAE,IAAI,CAAC;AACjB,QAAQ,EAAE,GAAG,CAAC;AACd;AACA,QAAQ,CAAC,GAAG,CAAC,SAAS,CAAC,eAAe,CAAC;AACvC,UAAU,CAAC,EAAE,CAAC,SAAS,EAAE,EAAE,CAAC;AAC5B,UAAU,CAAC,KAAK,CAAC,SAAS,CAAC,aAAa,CAAC;AACzC,YAAY,CAAC,KAAK,CAAC;AACnB,cAAc,CAAC,EAAE,CAAC;AAClB,gBAAgB,CAAC,EAAE,CAAC,SAAS,EAAE,EAAE,CAAC;AAClC,gBAAgB,CAAC,EAAE,CAAC,IAAI,EAAE,EAAE,CAAC;AAC7B,cAAc,EAAE,EAAE,CAAC;AACnB,YAAY,EAAE,KAAK,CAAC;AACpB,YAAY,CAAC,KAAK,CAAC;AACnB,cAAc,CAACxB,KAAK,CAACyB,MAAM,GAAG,CAAC,GACfzB,KAAK,CAAC0B,GAAG,CAACL,IAAI,IACZ,CAAC,EAAE,CAAC,GAAG,CAAC,CAACA,IAAI,CAACP,EAAE,CAAC,CAAC;AACpC,oBAAoB,CAAC,EAAE,CAAC,CAACO,IAAI,CAACJ,QAAQ,CAAC,EAAE,EAAE,CAAC;AAC5C,oBAAoB,CAAC,EAAE,CAAC,CAACI,IAAI,CAACH,IAAI,CAAC,EAAE,EAAE,CAAC;AACxC,kBAAkB,EAAE,EAAE,CACL,CAAC,GAEF,CAAC,EAAE,CAAC;AACpB,kBAAkB,CAAC,EAAE,CAAC,OAAO,CAAC,GAAG,CAAC,KAAK,CAAC,CAAC;gBAAES,SAAS,EAAE,QAAQ;gBAAEC,SAAS,EAAE,QAAQ;gBAAEC,KAAK,EAAE;cAA2B,CAAC,CAAC,CAAC,eAAe,EAAE,EAAE,CAAC;AAC9I,gBAAgB,EAAE,EAAE,CACL,CAAC;AAChB,YAAY,EAAE,KAAK,CAAC;AACpB,UAAU,EAAE,KAAK,CAAC;AAClB,QAAQ,EAAE,GAAG,CAAC;AACd,MAAM,EAAE,GAAG,CAAC;AACZ,IAAI,EAAE,GAAG,CAAC;AAEV,CAAC;AAAC9B,EAAA,CApHWD,UAAU;AAAAgC,EAAA,GAAVhC,UAAU;AAAA,IAAAgC,EAAA;AAAAC,YAAA,CAAAD,EAAA","ignoreList":[]}}},"code":"!function (module1) {\n  var _toConsumableArray;\n  module1.link(\"@babel/runtime/helpers/toConsumableArray\", {\n    default: function (v) {\n      _toConsumableArray = v;\n    }\n  }, 0);\n  var _slicedToArray;\n  module1.link(\"@babel/runtime/helpers/slicedToArray\", {\n    default: function (v) {\n      _slicedToArray = v;\n    }\n  }, 1);\n  module1.export({\n    AdminPanel: function () {\n      return AdminPanel;\n    }\n  });\n  var React, useState;\n  module1.link(\"react\", {\n    \"default\": function (v) {\n      React = v;\n    },\n    useState: function (v) {\n      useState = v;\n    }\n  }, 0);\n  ___INIT_METEOR_FAST_REFRESH(module);\n  var _s = $RefreshSig$();\n  var AdminPanel = function () {\n    _s();\n    var _useState = useState([]),\n      _useState2 = _slicedToArray(_useState, 2),\n      users = _useState2[0],\n      setUsers = _useState2[1];\n    var _useState3 = useState(''),\n      _useState4 = _slicedToArray(_useState3, 2),\n      newUsername = _useState4[0],\n      setNewUsername = _useState4[1];\n    var _useState5 = useState(''),\n      _useState6 = _slicedToArray(_useState5, 2),\n      newPassword = _useState6[0],\n      setNewPassword = _useState6[1];\n    var _useState7 = useState(''),\n      _useState8 = _slicedToArray(_useState7, 2),\n      deleteUsername = _useState8[0],\n      setDeleteUsername = _useState8[1];\n    var handleAddUser = function (e) {\n      e.preventDefault();\n      if (newUsername.trim() === '') {\n        alert('Please enter a username.');\n        return;\n      }\n      var newUser = {\n        id: Date.now(),\n        // simple unique id\n        username: newUsername,\n        role: 'User'\n      };\n      setUsers([].concat(_toConsumableArray(users), [newUser]));\n      setNewUsername('');\n      setNewPassword('');\n    };\n    var handleDeleteUser = function (e) {\n      e.preventDefault();\n      if (deleteUsername.trim() === '') {\n        alert('Please enter a username to delete.');\n        return;\n      }\n      if (!users.find(function (user) {\n        return user.username === deleteUsername;\n      })) {\n        alert('User not found.');\n        return;\n      }\n      setUsers(users.filter(function (user) {\n        return user.username !== deleteUsername;\n      }));\n      setDeleteUsername('');\n    };\n    return /*#__PURE__*/React.createElement(\"div\", {\n      className: \"admin-panel\"\n    }, /*#__PURE__*/React.createElement(\"div\", {\n      className: \"admin-header\"\n    }, /*#__PURE__*/React.createElement(\"h1\", null, \"Welcome to the Admin Panel\"), /*#__PURE__*/React.createElement(\"p\", {\n      className: \"admin-user-role\"\n    }, \"User as Admin\")), /*#__PURE__*/React.createElement(\"div\", {\n      className: \"admin-content\"\n    }, /*#__PURE__*/React.createElement(\"div\", {\n      className: \"admin-section\"\n    }, /*#__PURE__*/React.createElement(\"form\", {\n      className: \"admin-form horizontal-form\",\n      onSubmit: handleAddUser\n    }, /*#__PURE__*/React.createElement(\"div\", {\n      className: \"form-group\"\n    }, /*#__PURE__*/React.createElement(\"label\", {\n      htmlFor: \"username\"\n    }, \"User Name\"), /*#__PURE__*/React.createElement(\"input\", {\n      type: \"text\",\n      id: \"username\",\n      name: \"username\",\n      placeholder: \"Enter new user's name\",\n      value: newUsername,\n      onChange: function (e) {\n        return setNewUsername(e.target.value);\n      }\n    })), /*#__PURE__*/React.createElement(\"div\", {\n      className: \"form-group\"\n    }, /*#__PURE__*/React.createElement(\"label\", {\n      htmlFor: \"password\"\n    }, \"Password\"), /*#__PURE__*/React.createElement(\"input\", {\n      type: \"password\",\n      id: \"password\",\n      name: \"password\",\n      placeholder: \"Enter password\",\n      value: newPassword,\n      onChange: function (e) {\n        return setNewPassword(e.target.value);\n      }\n    })), /*#__PURE__*/React.createElement(\"button\", {\n      type: \"submit\",\n      className: \"admin-button\"\n    }, \"Add User\"))), /*#__PURE__*/React.createElement(\"div\", {\n      className: \"admin-section\"\n    }, /*#__PURE__*/React.createElement(\"form\", {\n      className: \"admin-form horizontal-form\",\n      onSubmit: handleDeleteUser\n    }, /*#__PURE__*/React.createElement(\"div\", {\n      className: \"form-group\"\n    }, /*#__PURE__*/React.createElement(\"label\", {\n      htmlFor: \"delete-username\"\n    }, \"User Name\"), /*#__PURE__*/React.createElement(\"input\", {\n      type: \"text\",\n      id: \"delete-username\",\n      name: \"delete-username\",\n      placeholder: \"Enter user's name to delete\",\n      value: deleteUsername,\n      onChange: function (e) {\n        return setDeleteUsername(e.target.value);\n      }\n    })), /*#__PURE__*/React.createElement(\"button\", {\n      type: \"submit\",\n      className: \"admin-button danger\"\n    }, \"Delete User\"))), /*#__PURE__*/React.createElement(\"div\", {\n      className: \"admin-section\"\n    }, /*#__PURE__*/React.createElement(\"h2\", null, \"User List\"), /*#__PURE__*/React.createElement(\"table\", {\n      className: \"users-table\"\n    }, /*#__PURE__*/React.createElement(\"thead\", null, /*#__PURE__*/React.createElement(\"tr\", null, /*#__PURE__*/React.createElement(\"th\", null, \"User Name\"), /*#__PURE__*/React.createElement(\"th\", null, \"Role\"))), /*#__PURE__*/React.createElement(\"tbody\", null, users.length > 0 ? users.map(function (user) {\n      return /*#__PURE__*/React.createElement(\"tr\", {\n        key: user.id\n      }, /*#__PURE__*/React.createElement(\"td\", null, user.username), /*#__PURE__*/React.createElement(\"td\", null, user.role));\n    }) : /*#__PURE__*/React.createElement(\"tr\", null, /*#__PURE__*/React.createElement(\"td\", {\n      colSpan: \"2\",\n      style: {\n        textAlign: 'center',\n        fontStyle: 'italic',\n        color: 'rgba(255, 255, 255, 0.5)'\n      }\n    }, \"No users found.\")))))));\n  };\n  _s(AdminPanel, \"aN4+h7fB7VQi1faFsiFgTfpQ1ZI=\");\n  _c = AdminPanel;\n  var _c;\n  $RefreshReg$(_c, \"AdminPanel\");\n}.call(this, module);","map":{"version":3,"names":["AdminPanel","_s","_useState","useState","_useState2","_slicedToArray","users","setUsers","_useState3","_useState4","newUsername","setNewUsername","_useState5","_useState6","newPassword","setNewPassword","_useState7","_useState8","deleteUsername","setDeleteUsername","handleAddUser","e","preventDefault","trim","alert","newUser","id","Date","now","username","role","concat","_toConsumableArray","handleDeleteUser","find","user","filter","React","createElement","className","onSubmit","htmlFor","type","name","placeholder","value","onChange","target","length","map","key","colSpan","style","textAlign","fontStyle","color","_c","$RefreshReg$","call","module"],"sources":["imports/ui/AdminPanel.jsx"],"sourcesContent":["import React, { useState } from 'react';\r\n\r\nexport const AdminPanel = () => {\r\n  const [users, setUsers] = useState([]);\r\n  const [newUsername, setNewUsername] = useState('');\r\n  const [newPassword, setNewPassword] = useState('');\r\n  const [deleteUsername, setDeleteUsername] = useState('');\r\n\r\n  const handleAddUser = (e) => {\r\n    e.preventDefault();\r\n    if (newUsername.trim() === '') {\r\n      alert('Please enter a username.');\r\n      return;\r\n    }\r\n    const newUser = {\r\n      id: Date.now(), // simple unique id\r\n      username: newUsername,\r\n      role: 'User',\r\n    };\r\n    setUsers([...users, newUser]);\r\n    setNewUsername('');\r\n    setNewPassword('');\r\n  };\r\n\r\n  const handleDeleteUser = (e) => {\r\n    e.preventDefault();\r\n    if (deleteUsername.trim() === '') {\r\n      alert('Please enter a username to delete.');\r\n      return;\r\n    }\r\n    if (!users.find(user => user.username === deleteUsername)) {\r\n      alert('User not found.');\r\n      return;\r\n    }\r\n    setUsers(users.filter(user => user.username !== deleteUsername));\r\n    setDeleteUsername('');\r\n  };\r\n\r\n  return (\r\n    <div className=\"admin-panel\">\r\n      <div className=\"admin-header\">\r\n        <h1>Welcome to the Admin Panel</h1>\r\n        <p className=\"admin-user-role\">User as Admin</p>\r\n      </div>\r\n      <div className=\"admin-content\">\r\n        <div className=\"admin-section\">\r\n          <form className=\"admin-form horizontal-form\" onSubmit={handleAddUser}>\r\n            <div className=\"form-group\">\r\n              <label htmlFor=\"username\">User Name</label>\r\n              <input \r\n                type=\"text\" \r\n                id=\"username\" \r\n                name=\"username\" \r\n                placeholder=\"Enter new user's name\" \r\n                value={newUsername}\r\n                onChange={(e) => setNewUsername(e.target.value)}\r\n              />\r\n            </div>\r\n            <div className=\"form-group\">\r\n              <label htmlFor=\"password\">Password</label>\r\n              <input \r\n                type=\"password\" \r\n                id=\"password\" \r\n                name=\"password\" \r\n                placeholder=\"Enter password\" \r\n                value={newPassword}\r\n                onChange={(e) => setNewPassword(e.target.value)}\r\n              />\r\n            </div>\r\n            <button type=\"submit\" className=\"admin-button\">Add User</button>\r\n          </form>\r\n        </div>\r\n\r\n        <div className=\"admin-section\">\r\n          <form className=\"admin-form horizontal-form\" onSubmit={handleDeleteUser}>\r\n            <div className=\"form-group\">\r\n              <label htmlFor=\"delete-username\">User Name</label>\r\n              <input \r\n                type=\"text\" \r\n                id=\"delete-username\" \r\n                name=\"delete-username\" \r\n                placeholder=\"Enter user's name to delete\" \r\n                value={deleteUsername}\r\n                onChange={(e) => setDeleteUsername(e.target.value)}\r\n              />\r\n            </div>\r\n            <button type=\"submit\" className=\"admin-button danger\">Delete User</button>\r\n          </form>\r\n        </div>\r\n\r\n        <div className=\"admin-section\">\r\n          <h2>User List</h2>\r\n          <table className=\"users-table\">\r\n            <thead>\r\n              <tr>\r\n                <th>User Name</th>\r\n                <th>Role</th>\r\n              </tr>\r\n            </thead>\r\n            <tbody>\r\n              {users.length > 0 ? (\r\n                users.map(user => (\r\n                  <tr key={user.id}>\r\n                    <td>{user.username}</td>\r\n                    <td>{user.role}</td>\r\n                  </tr>\r\n                ))\r\n              ) : (\r\n                <tr>\r\n                  <td colSpan=\"2\" style={{ textAlign: 'center', fontStyle: 'italic', color: 'rgba(255, 255, 255, 0.5)' }}>No users found.</td>\r\n                </tr>\r\n              )}\r\n            </tbody>\r\n          </table>\r\n        </div>\r\n      </div>\r\n    </div>\r\n  );\r\n};\r\n"],"mappings":";;;;;;;;;;;;;;;;;;;;;;;;;;;;;EAEO,IAAMA,UAAU,GAAG,SAAAA,CAAA,EAAM;IAAAC,EAAA;IAC9B,IAAAC,SAAA,GAA0BC,QAAQ,CAAC,EAAE,CAAC;MAAAC,UAAA,GAAAC,cAAA,CAAAH,SAAA;MAA/BI,KAAK,GAAAF,UAAA;MAAEG,QAAQ,GAAAH,UAAA;IACtB,IAAAI,UAAA,GAAsCL,QAAQ,CAAC,EAAE,CAAC;MAAAM,UAAA,GAAAJ,cAAA,CAAAG,UAAA;MAA3CE,WAAW,GAAAD,UAAA;MAAEE,cAAc,GAAAF,UAAA;IAClC,IAAAG,UAAA,GAAsCT,QAAQ,CAAC,EAAE,CAAC;MAAAU,UAAA,GAAAR,cAAA,CAAAO,UAAA;MAA3CE,WAAW,GAAAD,UAAA;MAAEE,cAAc,GAAAF,UAAA;IAClC,IAAAG,UAAA,GAA4Cb,QAAQ,CAAC,EAAE,CAAC;MAAAc,UAAA,GAAAZ,cAAA,CAAAW,UAAA;MAAjDE,cAAc,GAAAD,UAAA;MAAEE,iBAAiB,GAAAF,UAAA;IAExC,IAAMG,aAAa,GAAI,SAAAA,CAAAC,CAAC,EAAK;MAC3BA,CAAC,CAACC,cAAc,CAAC,CAAC;MAClB,IAAIZ,WAAW,CAACa,IAAI,CAAC,CAAC,KAAK,EAAE,EAAE;QAC7BC,KAAK,CAAC,0BAA0B,CAAC;QACjC;MACF;MACA,IAAMC,OAAO,GAAG;QACdC,EAAE,EAAEC,IAAI,CAACC,GAAG,CAAC,CAAC;QAAE;QAChBC,QAAQ,EAAEnB,WAAW;QACrBoB,IAAI,EAAE;MACR,CAAC;MACDvB,QAAQ,IAAAwB,MAAA,CAAAC,kBAAA,CAAK1B,KAAK,IAAEmB,OAAO,EAAC,CAAC;MAC7Bd,cAAc,CAAC,EAAE,CAAC;MAClBI,cAAc,CAAC,EAAE,CAAC;IACpB,CAAC;IAED,IAAMkB,gBAAgB,GAAI,SAAAA,CAAAZ,CAAC,EAAK;MAC9BA,CAAC,CAACC,cAAc,CAAC,CAAC;MAClB,IAAIJ,cAAc,CAACK,IAAI,CAAC,CAAC,KAAK,EAAE,EAAE;QAChCC,KAAK,CAAC,oCAAoC,CAAC;QAC3C;MACF;MACA,IAAI,CAAClB,KAAK,CAAC4B,IAAI,CAAC,UAAAC,IAAI;QAAA,OAAIA,IAAI,CAACN,QAAQ,KAAKX,cAAc;MAAA,EAAC,EAAE;QACzDM,KAAK,CAAC,iBAAiB,CAAC;QACxB;MACF;MACAjB,QAAQ,CAACD,KAAK,CAAC8B,MAAM,CAAC,UAAAD,IAAI;QAAA,OAAIA,IAAI,CAACN,QAAQ,KAAKX,cAAc;MAAA,EAAC,CAAC;MAChEC,iBAAiB,CAAC,EAAE,CAAC;IACvB,CAAC;IAED,oBACEkB,KAAA,CAAAC,aAAA;MAAKC,SAAS,EAAC;IAAa,gBAC1BF,KAAA,CAAAC,aAAA;MAAKC,SAAS,EAAC;IAAc,gBAC3BF,KAAA,CAAAC,aAAA,aAAI,4BAA8B,CAAC,eACnCD,KAAA,CAAAC,aAAA;MAAGC,SAAS,EAAC;IAAiB,GAAC,eAAgB,CAC5C,CAAC,eACNF,KAAA,CAAAC,aAAA;MAAKC,SAAS,EAAC;IAAe,gBAC5BF,KAAA,CAAAC,aAAA;MAAKC,SAAS,EAAC;IAAe,gBAC5BF,KAAA,CAAAC,aAAA;MAAMC,SAAS,EAAC,4BAA4B;MAACC,QAAQ,EAAEpB;IAAc,gBACnEiB,KAAA,CAAAC,aAAA;MAAKC,SAAS,EAAC;IAAY,gBACzBF,KAAA,CAAAC,aAAA;MAAOG,OAAO,EAAC;IAAU,GAAC,WAAgB,CAAC,eAC3CJ,KAAA,CAAAC,aAAA;MACEI,IAAI,EAAC,MAAM;MACXhB,EAAE,EAAC,UAAU;MACbiB,IAAI,EAAC,UAAU;MACfC,WAAW,EAAC,uBAAuB;MACnCC,KAAK,EAAEnC,WAAY;MACnBoC,QAAQ,EAAG,SAAAA,CAAAzB,CAAC;QAAA,OAAKV,cAAc,CAACU,CAAC,CAAC0B,MAAM,CAACF,KAAK,CAAC;MAAA;IAAC,EAE/C,CAAC,eACNR,KAAA,CAAAC,aAAA;MAAKC,SAAS,EAAC;IAAY,gBACzBF,KAAA,CAAAC,aAAA;MAAOG,OAAO,EAAC;IAAU,GAAC,UAAe,CAAC,eAC1CJ,KAAA,CAAAC,aAAA;MACEI,IAAI,EAAC,UAAU;MACfhB,EAAE,EAAC,UAAU;MACbiB,IAAI,EAAC,UAAU;MACfC,WAAW,EAAC,gBAAgB;MAC5BC,KAAK,EAAE/B,WAAY;MACnBgC,QAAQ,EAAG,SAAAA,CAAAzB,CAAC;QAAA,OAAKN,cAAc,CAACM,CAAC,CAAC0B,MAAM,CAACF,KAAK,CAAC;MAAA;IAAC,EAE/C,CAAC,eACNR,KAAA,CAAAC,aAAA;MAAQI,IAAI,EAAC,QAAQ;MAACH,SAAS,EAAC;IAAc,GAAC,UAAgB,CAC3D,CACH,CAAC,eAENF,KAAA,CAAAC,aAAA;MAAKC,SAAS,EAAC;IAAe,gBAC5BF,KAAA,CAAAC,aAAA;MAAMC,SAAS,EAAC,4BAA4B;MAACC,QAAQ,EAAEP;IAAiB,gBACtEI,KAAA,CAAAC,aAAA;MAAKC,SAAS,EAAC;IAAY,gBACzBF,KAAA,CAAAC,aAAA;MAAOG,OAAO,EAAC;IAAiB,GAAC,WAAgB,CAAC,eAClDJ,KAAA,CAAAC,aAAA;MACEI,IAAI,EAAC,MAAM;MACXhB,EAAE,EAAC,iBAAiB;MACpBiB,IAAI,EAAC,iBAAiB;MACtBC,WAAW,EAAC,6BAA6B;MACzCC,KAAK,EAAE3B,cAAe;MACtB4B,QAAQ,EAAG,SAAAA,CAAAzB,CAAC;QAAA,OAAKF,iBAAiB,CAACE,CAAC,CAAC0B,MAAM,CAACF,KAAK,CAAC;MAAA;IAAC,EAElD,CAAC,eACNR,KAAA,CAAAC,aAAA;MAAQI,IAAI,EAAC,QAAQ;MAACH,SAAS,EAAC;IAAqB,GAAC,aAAmB,CACrE,CACH,CAAC,eAENF,KAAA,CAAAC,aAAA;MAAKC,SAAS,EAAC;IAAe,gBAC5BF,KAAA,CAAAC,aAAA,aAAI,WAAa,CAAC,eAClBD,KAAA,CAAAC,aAAA;MAAOC,SAAS,EAAC;IAAa,gBAC5BF,KAAA,CAAAC,aAAA,6BACED,KAAA,CAAAC,aAAA,0BACED,KAAA,CAAAC,aAAA,aAAI,WAAa,CAAC,eAClBD,KAAA,CAAAC,aAAA,aAAI,MAAQ,CACV,CACC,CAAC,eACRD,KAAA,CAAAC,aAAA,gBACGhC,KAAK,CAAC0C,MAAM,GAAG,CAAC,GACf1C,KAAK,CAAC2C,GAAG,CAAC,UAAAd,IAAI;MAAA,oBACZE,KAAA,CAAAC,aAAA;QAAIY,GAAG,EAAEf,IAAI,CAACT;MAAG,gBACfW,KAAA,CAAAC,aAAA,aAAKH,IAAI,CAACN,QAAa,CAAC,eACxBQ,KAAA,CAAAC,aAAA,aAAKH,IAAI,CAACL,IAAS,CACjB,CACL;IAAA,EAAC,gBAEFO,KAAA,CAAAC,aAAA,0BACED,KAAA,CAAAC,aAAA;MAAIa,OAAO,EAAC,GAAG;MAACC,KAAK,EAAE;QAAEC,SAAS,EAAE,QAAQ;QAAEC,SAAS,EAAE,QAAQ;QAAEC,KAAK,EAAE;MAA2B;IAAE,GAAC,iBAAmB,CACzH,CAED,CACF,CACJ,CACF,CACF,CAAC;EAEV,CAAC;EAACtD,EAAA,CApHWD,UAAU;EAAAwD,EAAA,GAAVxD,UAAU;EAAA,IAAAwD,EAAA;EAAAC,YAAA,CAAAD,EAAA;AAAA,EAAAE,IAAA,OAAAC,MAAA","ignoreList":[]},"sourceType":"module","externalDependencies":{},"hash":"6e8cd6d80f0ea7ffa4eb1f45a4014ab165b998c0"}
